<?xml version="1.0" ?>

<container xmlns="http://symfony.com/schema/dic/services"
           xmlns:xsi="http://www.w3.org/2001/XMLSchema-instance"
           xsi:schemaLocation="http://symfony.com/schema/dic/services http://symfony.com/schema/dic/services/services-1.0.xsd">

    <services>
        <service id="nv.request_limit.request_restrictor" class="NV\RequestLimitBundle\Utils\RequestRestrictor" public="true">
                <argument type="service" id="nv.request_limit.storage_manager" />
        </service>

        <service id="nv.request_limit.storage_manager" class="NV\RequestLimitBundle\Storage\StorageManager"/>

        <!-- Providers definitions below -->
        <service id="nv.request_limit.memcached.provider" class="NV\RequestLimitBundle\Storage\Provider\MemcachedProvider"/>

        <service id="nv.request_limit.memcached.provider" class="NV\RequestLimitBundle\Storage\Provider\MySQLProvider">
            <argument type="service" id="doctrine.orm.default_entity_manager" />
        </service>

        <!-- Restrictions data collector -->
        <service id="nv.request_limit.restrictions_collector" class="NV\RequestLimitBundle\DataCollector\RestrictionsCollector">
            <call method="setStorageManager">
                <argument type="service" id="nv.request_limit.storage_manager" />
            </call>

            <tag name="data_collector" template="NVRequestLimitBundle:DataCollector:restrictions"
                 id="nv.request_limit.restrictions_collector"/>
        </service>
    </services>
</container>
